{"data":{"site":{"siteMetadata":{"shortname":"secret-unspoken"}},"markdownRemark":{"html":"<p>I've been asked how I have been working on my own recovery, and I get the sense that most people are listening for a silver bullet. I think the best way to answer this is to continue the story that I have been telling.</p>\n<p>I finished the <a href=\"https://secret-unspoken.github.io/posts/moving-on-and-getting-over/\">last post</a> with what I had learned coming away from <a href=\"https://faithfulandtrue.com/\">Faithful &#x26; True</a>, that I needed to work on the addiction directly, emotional and mental health, and on community. So how did I go about that?</p>\n<p>Let's start with the program. Similar to Alcoholic's Anonymous' 12 steps, there are 7 steps to this program, which follow quite closely. There is no need to get into it, except to note that, like AA, there is no silver bullet to conquering the addiction. But following the program does yield results. At a high level, it involves admitting unmanageability and surrending control, accepting help from God as you understand him, accountability inside of community, reparations, and spreading hope to others.</p>\n<p>Let's start with the program: 12 step\nrussel brand\nfirst 60 days\nbiological: break from the stimulus\nmaking sense of my past\nunderstanding my own emotional history\nHow i learned to cope\nWhat I need to learn now to cope\nCommunity</p>","frontmatter":{"title":"Part Two: Recovery","date":"11 November, 2018"},"fields":{"slug":"/posts/recovery/"},"wordCount":{"words":204}}},"pageContext":{"slug":"/posts/recovery/","prev":{"frontmatter":{"type":"post","title":"Moving on and getting over"},"fields":{"slug":"/posts/moving-on-and-getting-over/"}},"next":false}}