{"data":{"markdownRemark":{"html":"<p>Lorem ipsum dolor sit amet, consectetur adipiscing elit. Vestibulum congue pharetra odio, ac hendrerit nibh rhoncus et. Suspendisse nibh enim, hendrerit quis diam a, egestas euismod dolor. Phasellus turpis mauris, condimentum non sollicitudin quis, maximus vel odio. In hendrerit tristique laoreet. Integer turpis justo, blandit in nibh ut, pellentesque viverra elit. Curabitur vitae varius ante. Proin vulputate, lectus id pharetra laoreet, quam lacus aliquet libero, in porttitor nulla nunc a nisi. Morbi consectetur suscipit faucibus. Phasellus ut ultricies erat. Ut ullamcorper pharetra nunc. Cras malesuada eleifend magna, et dapibus nisl.</p>\n<p>Ut mattis, elit in mollis porttitor, odio nisi placerat massa, vitae pellentesque nunc tellus et sapien. Sed a tortor nec est vestibulum iaculis vitae ac dolor. Maecenas posuere ornare mi, varius tempus odio sagittis nec. Praesent iaculis eros nec augue mattis, sit amet venenatis dolor hendrerit. Phasellus tincidunt, purus at aliquet finibus, quam nunc varius quam, et luctus turpis sem quis dolor. Nullam sem neque, convallis nec dapibus ac, dapibus congue nibh. Vestibulum dapibus nisl nisi, at aliquet leo sollicitudin eget. Pellentesque lacus magna, laoreet id sem et, vulputate porttitor nibh. Vestibulum quis rutrum felis. In hac habitasse platea dictumst. Aliquam eu leo nec nunc laoreet condimentum. Suspendisse consectetur pulvinar ligula eu lacinia. Maecenas rhoncus ante nec mauris euismod convallis. Suspendisse maximus urna eu tristique lacinia.</p>\n<p>Aenean lacus tortor, placerat ut sodales a, interdum in orci. Morbi ac diam et nibh malesuada rutrum id at augue. Morbi porta tincidunt dolor, sit amet blandit arcu iaculis vitae. Mauris vel mi magna. Maecenas facilisis pellentesque arcu ut ullamcorper. Mauris eget mi scelerisque, rutrum elit in, pellentesque dolor. Mauris sed velit rhoncus mi porttitor tristique. Nam gravida, elit vel pharetra gravida, orci dolor consectetur diam, et congue elit mi eget tortor. Phasellus at sapien nec enim eleifend pellentesque at sit amet erat. Duis scelerisque arcu turpis, sit amet egestas nisi ornare sit amet. Vestibulum eget felis nec ipsum hendrerit aliquam a quis velit.</p>\n<p>Mauris aliquam ut ligula ut venenatis. Maecenas pulvinar ex nec viverra sollicitudin. Maecenas eu mauris a neque sodales tristique. Nullam lorem dui, condimentum eu gravida sit amet, varius in ex. Phasellus et ultricies magna. Pellentesque habitant morbi tristique senectus et netus et malesuada fames ac turpis egestas. Vestibulum pretium, lorem vel aliquam euismod, ligula felis consequat mauris, eu dapibus nisl nisi tincidunt libero. Nunc ut sollicitudin metus, et elementum est. Sed tellus lorem, rhoncus in nisl egestas, placerat tempus orci. Etiam consequat lectus vel leo fringilla, eget rhoncus eros ultrices. Nullam tellus metus, dignissim nec luctus id, placerat eu ipsum. Aliquam magna leo, ornare quis hendrerit ac, viverra id tortor. Proin sagittis lacus non magna feugiat, id finibus sem convallis.</p>\n<p>Ut efficitur massa ligula, ac rhoncus velit ultricies eget. Etiam et massa sit amet sem efficitur ultricies commodo vel enim. Orci varius natoque penatibus et magnis dis parturient montes, nascetur ridiculus mus. Aenean convallis tincidunt leo nec venenatis. Cras molestie dui at efficitur facilisis. Vivamus tortor augue, lacinia a enim sit amet, lobortis sodales eros. Nunc ligula quam, ullamcorper ut diam ut, condimentum porta elit. Donec tellus elit, pulvinar nec suscipit varius, volutpat non magna. Maecenas tellus purus, ornare quis feugiat nec, mattis ut orci.</p>","frontmatter":{"title":"Quisque eu felis egestas, suscipit"}}},"pageContext":{"slug":"/my-story/"}}